{"nxifQW6rfEU/2q+Bk7rrKQ==":"schermata-2021-06-15-alle-15.12.52.png","lfWeIV6PEdzhP1xl4zx4QA==":"schermata-2021-06-21-alle-13.54.33.png","7dNs1+43votlrRai710K/w==":"mbr.jpg","lsfmQVsWnVg9lgHf9sA+dQ==":"-b4c0556.jpg","bH/cOnuQixwhMYoJj7ktVw==":"-b4c0589.jpg","xzfKcKnHnTHkdYL7Wg3TAQ==":"-b4c0632.jpg","Y5YGe2SODDWH5nL6GJuR8Q==":"-b4c0600.jpg","Q3Iy98t36yM/pkqXwvrg8Q==":"background7.jpg","Gk5MV9yBgbR4Tj2lq+yBAw==":"mbr-1.jpg","r1S/DZc97IP2K3FC84vgEQ==":"mbr-2.jpg","rmSX1dJPiuTCq6qmEx5lgg==":"ooj_aware+nh-1197x628.jpg","++GldA3zlCue8E0E3Jr4ag==":"aware%20(1)-1024x768.jpg"}